aioboto3-stubs/__init__.pyi
aioboto3-stubs/py.typed
aioboto3-stubs/session.pyi
aioboto3-stubs/dynamodb/__init__.pyi
aioboto3-stubs/dynamodb/table.pyi
aioboto3-stubs/experimental/__init__.pyi
aioboto3-stubs/experimental/async_chalice.pyi
aioboto3-stubs/resources/__init__.pyi
aioboto3-stubs/resources/action.pyi
aioboto3-stubs/resources/base.pyi
aioboto3-stubs/resources/collection.pyi
aioboto3-stubs/resources/factory.pyi
aioboto3-stubs/resources/response.pyi
aioboto3-stubs/s3/__init__.pyi
aioboto3-stubs/s3/cse.pyi
aioboto3-stubs/s3/inject.pyi
types_aioboto3_lite-15.4.0.dist-info/licenses/LICENSE
types_aioboto3_lite-15.4.0.dist-info/METADATA
types_aioboto3_lite-15.4.0.dist-info/WHEEL
types_aioboto3_lite-15.4.0.dist-info/top_level.txt
types_aioboto3_lite-15.4.0.dist-info/RECORD
